coder_coder/__init__.py
coder_coder/cli.py
coder_coder/content.py
coder_coder/main.py
coder_coder-0.2.1.dist-info/METADATA
coder_coder-0.2.1.dist-info/WHEEL
coder_coder-0.2.1.dist-info/entry_points.txt
coder_coder-0.2.1.dist-info/RECORD
